windstorm/__init__.py
windstorm/common/__init__.py
windstorm/common/api.py
windstorm/common/functions.py
windstorm/common/sysml.py
windstorm/main.py
windstorm/sample.yml
windstorm/sample_model.sysml
sysml_windstorm-0.5.6.dist-info/LICENSE
sysml_windstorm-0.5.6.dist-info/METADATA
sysml_windstorm-0.5.6.dist-info/WHEEL
sysml_windstorm-0.5.6.dist-info/entry_points.txt
sysml_windstorm-0.5.6.dist-info/RECORD
