Metadata-Version: 2.1
Name: sysml-windstorm
Version: 0.5.6
Summary: Tool to support SysMLv2 model templating for any text based file.
License: MIT
Author: Christopher Cox
Requires-Python: >=3.9,<4.0
Classifier: Development Status :: 3 - Alpha
Classifier: License :: OSI Approved :: MIT License
Classifier: Operating System :: OS Independent
Classifier: Programming Language :: Python :: 3
Classifier: Programming Language :: Python :: 3.9
Classifier: Programming Language :: Python :: 3.10
Classifier: Programming Language :: Python :: 3.11
Classifier: Programming Language :: Python :: 3.12
Classifier: Programming Language :: Python :: 3.13
Requires-Dist: fire (==0.6.0)
Requires-Dist: jinja2 (==3.1.4)
Requires-Dist: requests (==2.32.3)
